omnistack/__init__.py
omnistack/_base_client.py
omnistack/_client.py
omnistack/_compat.py
omnistack/_constants.py
omnistack/_exceptions.py
omnistack/_files.py
omnistack/_models.py
omnistack/_qs.py
omnistack/_resource.py
omnistack/_response.py
omnistack/_streaming.py
omnistack/_types.py
omnistack/_version.py
omnistack/py.typed
omnistack/_utils/__init__.py
omnistack/_utils/_logs.py
omnistack/_utils/_proxy.py
omnistack/_utils/_reflection.py
omnistack/_utils/_streams.py
omnistack/_utils/_sync.py
omnistack/_utils/_transform.py
omnistack/_utils/_typing.py
omnistack/_utils/_utils.py
omnistack/lib/.keep
omnistack/resources/__init__.py
omnistack/resources/batches.py
omnistack/resources/completions.py
omnistack/resources/embeddings.py
omnistack/resources/models.py
omnistack/resources/moderations.py
omnistack/resources/assistants/__init__.py
omnistack/resources/assistants/assistants.py
omnistack/resources/audio/__init__.py
omnistack/resources/audio/audio.py
omnistack/resources/audio/speech.py
omnistack/resources/audio/transcriptions.py
omnistack/resources/audio/translations.py
omnistack/resources/chats/__init__.py
omnistack/resources/chats/chats.py
omnistack/resources/chats/completions.py
omnistack/resources/files/__init__.py
omnistack/resources/files/content.py
omnistack/resources/files/files.py
omnistack/resources/fine_tuning/__init__.py
omnistack/resources/fine_tuning/fine_tuning.py
omnistack/resources/fine_tuning/jobs/__init__.py
omnistack/resources/fine_tuning/jobs/checkpoints.py
omnistack/resources/fine_tuning/jobs/events.py
omnistack/resources/fine_tuning/jobs/jobs.py
omnistack/resources/images/__init__.py
omnistack/resources/images/edits.py
omnistack/resources/images/generations.py
omnistack/resources/images/images.py
omnistack/resources/images/variations.py
omnistack/resources/organization/__init__.py
omnistack/resources/organization/audit_logs.py
omnistack/resources/organization/invites.py
omnistack/resources/organization/organization.py
omnistack-0.1.0a2.dist-info/METADATA
omnistack-0.1.0a2.dist-info/WHEEL
omnistack-0.1.0a2.dist-info/licenses/LICENSE
omnistack-0.1.0a2.dist-info/RECORD
